Metadata-Version: 2.1
Name: read-fillet
Version: 0.1.0
Summary: Splitting of sequence reads by internal adapter sequence search.
Home-page: https://github.com/epi2me-labs/read_fillet
Author: ont-research
Author-email: ont-research@nanoporetech.com
License: UNKNOWN
Platform: UNKNOWN
License-File: LICENSE.md
